dms2dec/__init__.py
dms2dec/dms_convert.py
dms2dec-0.1.dist-info/DESCRIPTION.rst
dms2dec-0.1.dist-info/METADATA
dms2dec-0.1.dist-info/RECORD
dms2dec-0.1.dist-info/WHEEL
dms2dec-0.1.dist-info/metadata.json
dms2dec-0.1.dist-info/top_level.txt
