Metadata-Version: 2.1
Name: dms2dec
Version: 0.1
Summary: DMS to decimal. Convert degrees minutes seconds to decimal latitude/longitude
Home-page: UNKNOWN
Author: 
Author-email: 
License: UNKNOWN
Platform: UNKNOWN
Classifier: Programming Language :: Python :: 3
Classifier: License :: OSI Approved :: GNU General Public License v3 or later (GPLv3+)
Classifier: Operating System :: OS Independent
Requires-Python: >=3
